{
  "venues": [
    {
      "name": "Pegola Paddington",
      "location": "5 Kingdom St, London, W2 6PY",
      "descriptionVenue": "Bar",
      "rating": 4,
      "id": 1
    },
    {
      "name": "Elements",
      "location": "3 Kingdom St, London, W2 6BD",
      "descriptionVenue": "Restaurant",
      "rating": 2,
      "id": 2
    },
    {
      "name": "Pure",
      "location": "2 Kingdom St, London, W2 6BD",
      "descriptionVenue": "club",
      "rating": 1,
      "id": 3
    },
    {
      "name": "Prince of Wales",
      "location": "2 Cleveland Terrace, London, W2 5LH",
      "descriptionVenue": "Restaurant",
      "rating": 3,
      "id": 4
    },
    {
      "name": "The Cleveland Arms",
      "location": "28 Chilworth Street, London, W2 6DT",
      "descriptionVenue": "Restaurant",
      "rating": "2",
      "id": 5
    },
    {
      "name": "Blizzaro",
      "location": "18-22 Craven Road, London, W2 3PX",
      "descriptionVenue": "Restaurant",
      "rating": "5",
      "id": 6
    },
    {
      "name": "The Bear",
      "location": "29 Spring Street, London, W2 1JA",
      "descriptionVenue": "Pub",
      "rating": "1",
      "id": 7
    }
  ]
}